ai_data_sdk/__init__.py
ai_data_sdk/client.py
ai_data_sdk/errors.py
ai_data_sdk/examples.py
ai_data_sdk-0.1.2.dist-info/METADATA
ai_data_sdk-0.1.2.dist-info/WHEEL
ai_data_sdk-0.1.2.dist-info/top_level.txt
ai_data_sdk-0.1.2.dist-info/RECORD
